{
	"Context":{
		"FX":{
			"Tonemapping":true,
			"SSAO":true,
			"ChromaticAberration":true,
			"FXAA":true,
			"MotionBlur":true,
			"Bloom":true
		},
		"Lumin":{
			"Enabled":false,
			"Viewport":{
				"Height":4096,
				"Width":4096
			}
		},
		"Lights":{
			"Viewport":{
				"Height":2048,
				"Width":2048
			}
		},
		"NoiseTextures":[{
				"Key":"TexSimplex",
				"Val":"Defaults/T_Noise_Simplex.json"
			},{
				"Key":"TexPerlin",
				"Val":"Defaults/T_Noise_Perlin.json"
			},{
				"Key":"TexCellular",
				"Val":"Defaults/T_Noise_Cellular.json"
			}
		]
	},
	"Viewport":{
		"Height":1758,
		"Width":2575
	},
	"Window":{
		"Height":1758,
		"Width":2892
	}
}