{
	"Data":{
		"Offset":[
			1.0,
			0.0,
			0.0,
			0.0,
			0.0,
			1.0,
			0.0,
			0.0,
			0.0,
			0.0,
			1.0,
			0.0,
			-8.0,
			-1.0,
			-1.999999761581421,
			1.0
		]
	},
	"Objects":[{
			"Blueprint":"Gameplay/Enemies/BP_Enemy.json",
			"Overrides":{
				"Components":[{
						"Name":"Mesh",
						"Data":{}
					},{
						"Name":"Attributes",
						"Data":{
							"Name":"Enemy"
						}
					},{
						"Name":"Transform",
						"Data":{
							"Position":[
								3.999999761581421,
								7.999999523162842,
								10.000000953674316
							]
						}
					},{
						"Name":"Collider",
						"Data":{}
					},{
						"Name":"Enemy",
						"Data":{}
					}
				]
			}
		},{
			"Blueprint":"Blueprints/BP_CubeVolume.json",
			"Overrides":{
				"Components":[{
						"Name":"Attributes",
						"Data":{
							"Name":"Unnamed5"
						}
					},{
						"Name":"Transform",
						"Data":{}
					},{
						"Name":"CubeVolume",
						"Data":{
							"Data":"1:131072,196608,589829,262144,524293,327680,393216,458752,655365,131074,524288,327685,65537,131073,196609,262145,589828,327681,524292,393217,458753,655364,524289,327684,589825,262148,131075,2,65538,196610,262146,327682,393218,458754,524290,589826,655362,3,65539,196611,262147,327683,393219,458755,524291,589827,655363,4,65540,131076,196612,393220,458756,5,65541,131077,196613,262149,393221,458757,6,65542,131078,196614,262150,327686,393222,458758,524294,262404,589830,655366,65543,131079,196615,262151,327687,393223,458759,524295,589831,131080,196616,262152,327688,393224,458760,524296,;"
						}
					}
				]
			}
		},{
			"Blueprint":"Gameplay/BP_RoomConnection.json",
			"Overrides":{
				"Components":[{
						"Name":"Attributes",
						"Data":{
							"Name":"RoomConnection"
						}
					},{
						"Name":"Transform",
						"Data":{
							"Position":[
								8.200000762939453,
								1.0,
								21.0
							]
						}
					},{
						"Name":"RoomConnection",
						"Data":{}
					}
				]
			}
		},{
			"Blueprint":"Gameplay/BP_RoomConnection.json",
			"Overrides":{
				"Components":[{
						"Name":"Attributes",
						"Data":{
							"Name":"RoomConnection"
						}
					},{
						"Name":"Transform",
						"Data":{
							"Position":[
								8.0,
								1.0,
								1.999999761581421
							]
						}
					},{
						"Name":"RoomConnection",
						"Data":{
							"IsEnd":false
						}
					}
				]
			}
		},{
			"Blueprint":"Gameplay/Player/BP_Sword.json",
			"Overrides":{
				"Components":[{
						"Name":"Attributes",
						"Data":{
							"Name":"Sword"
						}
					},{
						"Name":"Transform",
						"Data":{
							"Position":[
								8.0,
								4.0,
								8.0
							]
						}
					},{
						"Name":"Sword",
						"Data":{}
					}
				]
			}
		},{
			"Blueprint":"Gameplay/Enemies/BP_Enemy.json",
			"Overrides":{
				"Components":[{
						"Name":"Mesh",
						"Data":{}
					},{
						"Name":"Attributes",
						"Data":{
							"Name":"Enemy"
						}
					},{
						"Name":"Transform",
						"Data":{
							"Position":[
								14.0,
								4.0,
								18.0
							]
						}
					},{
						"Name":"Collider",
						"Data":{}
					},{
						"Name":"Enemy",
						"Data":{}
					}
				]
			}
		}
	]
}